CHANGES.txt
LICENSE.txt
MANIFEST.in
README.md
setup.py
cmsapp_rt/__init__.py
cmsapp_rt.egg-info/PKG-INFO
cmsapp_rt.egg-info/SOURCES.txt
cmsapp_rt.egg-info/dependency_links.txt
cmsapp_rt.egg-info/not-zip-safe
cmsapp_rt.egg-info/requires.txt
cmsapp_rt.egg-info/top_level.txt
cmsapp_rt/bsglobals/__init__.py
cmsapp_rt/bsglobals/admin.py
cmsapp_rt/bsglobals/context_processors.py
cmsapp_rt/bsglobals/models.py
cmsapp_rt/bsglobals/tests.py
cmsapp_rt/bsglobals/views.py
cmsapp_rt/bsglobals/fixtures/blank_globals.json
cmsapp_rt/bsglobals/migrations/0001_initial.py
cmsapp_rt/bsglobals/migrations/__init__.py
cmsapp_rt/bsglobals/templates/base.html