Metadata-Version: 1.0
Name: cmsapp-rt
Version: 0.0.4
Summary: This package contains one app (including a context processor and example template) to help your Django-CMS project work with Twitter Bootstrap
Home-page: https://github.com/RacingTadpole/cmsapp-rt
Author: Art Street
Author-email: art@racingtadpole.com
License: BSD License
Keywords: globals bootstrap racing tadpole
Platform: UNKNOWN
Classifier: Environment :: Web Environment
Classifier: Framework :: Django
Classifier: Intended Audience :: Developers
Classifier: License :: OSI Approved :: BSD License
Classifier: Operating System :: OS Independent
Classifier: Programming Language :: Python
Classifier: Programming Language :: Python :: 2.7
Classifier: Topic :: Internet :: WWW/HTTP
Classifier: Topic :: Internet :: WWW/HTTP :: Dynamic Content
